{
    "version": "2024.12.8",
    "description": "dev tools, env vars, task runner",
    "homepage": "https://mise.jdx.dev/",
    "license": "MIT",
    "notes": "",
    "architecture": {
        "64bit": {
            "url": "https://github.com/jdx/mise/releases/download/v2024.12.8/mise-v2024.12.8-windows-x64.zip",
            "hash": "6b6627144f2343c87c96f37474d7c0636e8b2fb76bb68a79105eb53be17e698b"
        },
        "arm64": {
            "url": "https://github.com/jdx/mise/releases/download/v2024.12.8/mise-v2024.12.8-windows-arm64.zip",
            "hash": "1d30d1d49af8ff76098e141b1b85386e5ea1b2d4efd97895267a16bfb8630200"
        }
    },
    "bin": "mise\\bin\\mise.exe",
    "checkver": {
        "github": "https://github.com/jdx/mise"
    },
    "autoupdate": {
        "architecture": {
            "64bit": {
                "url": "https://github.com/jdx/mise/releases/download/v$version/mise-v$version-windows-x64.zip"
            },
            "arm64": {
                "url": "https://github.com/jdx/mise/releases/download/v$version/mise-v$version-windows-arm64.zip"
            }
        },
        "hash": {
            "url": "$baseurl/SHASUM256.txt"
        }
    }
}
