{
    "version": "2025.7.7",
    "description": "dev tools, env vars, task runner",
    "homepage": "https://mise.jdx.dev/",
    "license": "MIT",
    "notes": "",
    "architecture": {
        "64bit": {
            "url": "https://github.com/jdx/mise/releases/download/v2025.7.7/mise-v2025.7.7-windows-x64.zip",
            "hash": "cba7a2c9205f187a240b2352b980497dd8795ae0010d01f3ec20c185e0e69b60"
        },
        "arm64": {
            "url": "https://github.com/jdx/mise/releases/download/v2025.7.7/mise-v2025.7.7-windows-arm64.zip",
            "hash": "d60892702b248dc919918f51f74f47fba1a88399407b2a980a68e9cfa2919688"
        }
    },
    "bin": "mise\\bin\\mise.exe",
    "checkver": {
        "github": "https://github.com/jdx/mise"
    },
    "autoupdate": {
        "architecture": {
            "64bit": {
                "url": "https://github.com/jdx/mise/releases/download/v$version/mise-v$version-windows-x64.zip"
            },
            "arm64": {
                "url": "https://github.com/jdx/mise/releases/download/v$version/mise-v$version-windows-arm64.zip"
            }
        },
        "hash": {
            "url": "$baseurl/SHASUM256.txt"
        }
    }
}
